norbert/__init__.py
norbert/contrib.py
norbert/utils.py
norbert-0.2.1.dist-info/LICENSE
norbert-0.2.1.dist-info/METADATA
norbert-0.2.1.dist-info/WHEEL
norbert-0.2.1.dist-info/top_level.txt
norbert-0.2.1.dist-info/RECORD
