Metadata-Version: 2.1
Name: norbert
Version: 0.2.1
Summary: Painless Wiener Filters
Home-page: https://github.com/sigsep/norbert
Author: Fabian-Robert Stoeter, Antoine Liutkus
License: UNKNOWN
Project-URL: Bug Reports, https://github.com/sigsep/norbert/issues
Keywords: wiener filter
Platform: UNKNOWN
Classifier: Development Status :: 4 - Beta
Classifier: Intended Audience :: Developers
Classifier: Topic :: Software Development :: Build Tools
Classifier: License :: OSI Approved :: MIT License
Classifier: Programming Language :: Python :: 3
Classifier: Programming Language :: Python :: 3.6
Classifier: Programming Language :: Python :: 3.7
Provides-Extra: docs
Provides-Extra: tests
Provides-Extra: dev
